BOWDN/__init__.py
BOWDN/command.py
BOWDN/command_catalogue.py
BOWDN/command_context.py
BOWDN/flag.py
bowdn-2.2.0.dist-info/METADATA
bowdn-2.2.0.dist-info/WHEEL
bowdn-2.2.0.dist-info/licenses/LICENSE
bowdn-2.2.0.dist-info/RECORD
